likhithapythonlibrary/__init__.py
likhithapythonlibrary/core.py
likhithapythonlibrary-0.0.3.dist-info/licenses/LICENSE.txt
likhithapythonlibrary-0.0.3.dist-info/METADATA
likhithapythonlibrary-0.0.3.dist-info/WHEEL
likhithapythonlibrary-0.0.3.dist-info/top_level.txt
likhithapythonlibrary-0.0.3.dist-info/RECORD
