Metadata-Version: 2.4
Name: likhithapythonlibrary
Version: 0.0.3
Summary: Short description of your package
Author: Likhitha Jayavarapu
Author-email: likhithaswapna703@gmail.com
License-File: LICENSE.txt
Dynamic: author
Dynamic: author-email
Dynamic: description
Dynamic: description-content-type
Dynamic: license-file
Dynamic: summary
